strlearn/__init__.py
strlearn/_version.py
strlearn/classifiers/ASC.py
strlearn/classifiers/SampleWeightedMetaEstimator.py
strlearn/classifiers/__init__.py
strlearn/ensembles/AUE.py
strlearn/ensembles/AWE.py
strlearn/ensembles/CDS.py
strlearn/ensembles/DWM.py
strlearn/ensembles/KMC.py
strlearn/ensembles/KUE.py
strlearn/ensembles/NIE.py
strlearn/ensembles/OOB.py
strlearn/ensembles/OUSE.py
strlearn/ensembles/OnlineBagging.py
strlearn/ensembles/REA.py
strlearn/ensembles/ROSE.py
strlearn/ensembles/SEA.py
strlearn/ensembles/UOB.py
strlearn/ensembles/WAE.py
strlearn/ensembles/__init__.py
strlearn/ensembles/base.py
strlearn/ensembles/pruning.py
strlearn/evaluators/Prequential.py
strlearn/evaluators/TestThenTrain.py
strlearn/evaluators/__init__.py
strlearn/metrics/__init__.py
strlearn/metrics/base.py
strlearn/streams/ARFFParser.py
strlearn/streams/CSVParser.py
strlearn/streams/NPYParser.py
strlearn/streams/SemiSyntheticStreamGenerator.py
strlearn/streams/StreamGenerator.py
strlearn/streams/__init__.py
strlearn/tests/__init__.py
strlearn/tests/test_classifiers.py
strlearn/tests/test_common.py
strlearn/tests/test_ensembles.py
strlearn/tests/test_evaluators.py
strlearn/tests/test_metrics.py
strlearn/tests/test_sklearn.py
strlearn/tests/test_streams.py
strlearn/utils/__init__.py
strlearn/utils/base.py
stream_learn-0.8.24.dist-info/LICENSE
stream_learn-0.8.24.dist-info/METADATA
stream_learn-0.8.24.dist-info/WHEEL
stream_learn-0.8.24.dist-info/top_level.txt
stream_learn-0.8.24.dist-info/RECORD
