Metadata-Version: 2.1
Name: stream-learn
Version: 0.8.24
Summary: The stream-learn module is a set of tools necessary for processing data streams using scikit-learn estimators.
Home-page: https://w4k2.github.io/stream-learn/
Download-URL: https://github.com/w4k2/stream-learn
Maintainer: P. Ksieniewicz
Maintainer-email: pawel.ksieniewicz@pwr.edu.pl
License: GPL-3.0
Classifier: Development Status :: 4 - Beta
Classifier: Intended Audience :: Science/Research
Classifier: License :: OSI Approved :: GNU General Public License v3 (GPLv3)
Classifier: Programming Language :: Python
Classifier: Programming Language :: Python :: 3.7
Classifier: Topic :: Scientific/Engineering
Classifier: Topic :: Scientific/Engineering :: Artificial Intelligence
Classifier: Topic :: Software Development :: Libraries
Classifier: Topic :: Software Development :: Libraries :: Python Modules
License-File: LICENSE
Requires-Dist: numpy
Requires-Dist: scipy
Requires-Dist: scikit-learn
Requires-Dist: imbalanced-learn
Requires-Dist: tqdm
Requires-Dist: problexity
